pyfdstools/__init__.py
pyfdstools/_version.py
pyfdstools/blender_examples.py
pyfdstools/check_csv_initialization.py
pyfdstools/colorSchemes.py
pyfdstools/example_paraview_export.py
pyfdstools/example_paraview_export_group_by_mesh.py
pyfdstools/examples.py
pyfdstools/extractBoundaryData.py
pyfdstools/extractCSVdata.py
pyfdstools/extractGeomData.py
pyfdstools/extractParticleData.py
pyfdstools/extractPlot3Ddata.py
pyfdstools/extractPolygon.py
pyfdstools/extractS3D.py
pyfdstools/fdsErrorCalculation.py
pyfdstools/fdsFileOperations.py
pyfdstools/fdsTypes.py
pyfdstools/inputFileVerification.py
pyfdstools/paraview.py
pyfdstools/preprocessing_initialization_greedy.py
pyfdstools/run_verification.py
pyfdstools/smokeviewParser.py
pyfdstools/utilities.py
pyfdstools/examples/dump_2d_slice_to_csv.py
pyfdstools/examples/dump_3d_slice_to_csv.py
pyfdstools/examples/error_calculation.py
pyfdstools/examples/extract_2d_slice_from_3d_slice.py
pyfdstools/examples/extract_2d_slice_from_pl3d.py
pyfdstools/examples/extract_boundary_data.py
pyfdstools/examples/extract_boundary_max.py
pyfdstools/examples/read_and_write_input_files.py
pyfdstools/examples/data/case001.fds
pyfdstools/examples/data/case001.zip
pyfdstools/examples/data/case002.zip
pyfdstools/examples/data/fed_example.fds
pyfdstools/examples/data/fed_example_occupants.csv
pyfdstools/examples/data/hfg_slice.zip
pyfdstools/examples/data/stretched_mesh_example.zip
pyfdstools/examples/data/visibility_adjustment.zip
pyfdstools/examples/data/case001/case001.binfo
pyfdstools/examples/data/case001/case001.fds
pyfdstools/examples/data/case001/case001.out
pyfdstools/examples/data/case001/case001.prt.gbnd
pyfdstools/examples/data/case001/case001.sinfo
pyfdstools/examples/data/case001/case001.smv
pyfdstools/examples/data/case001/case001_1.prt5
pyfdstools/examples/data/case001/case001_1.prt5.bnd
pyfdstools/examples/data/case001/case001_1.prt5.sz
pyfdstools/examples/data/case001/case001_1.xyz
pyfdstools/examples/data/case001/case001_1_1.bf
pyfdstools-0.0.22.dist-info/licenses/LICENSE.txt
pyfdstools-0.0.22.dist-info/METADATA
pyfdstools-0.0.22.dist-info/WHEEL
pyfdstools-0.0.22.dist-info/top_level.txt
pyfdstools-0.0.22.dist-info/RECORD
