Metadata-Version: 2.4
Name: pyfdstools
Version: 0.0.22
Summary: This software is part of a python library to assist in developing and analyzing simulation results from Fire Dynamics Simulator (FDS). FDS is an open source computational fluid dynamics (CFD) software package developed by NIST. The sourcecode is available at: https://github.com/firemodels/fds
Home-page: https://github.com/johodges/pyfdstools
Author: Jonathan Hodges
Author-email: johodges@vt.edu
License: MIT
Classifier: Development Status :: 1 - Planning
Classifier: Intended Audience :: Science/Research
Classifier: License :: OSI Approved :: MIT License
Classifier: Operating System :: OS Independent
Classifier: Programming Language :: Python :: 3
Classifier: Programming Language :: Python :: 3.4
Classifier: Programming Language :: Python :: 3.5
License-File: LICENSE.txt
Requires-Dist: libopencv>=0.0.1
Requires-Dist: matplotlib>=3.0
Requires-Dist: numpy>=1.17
Requires-Dist: numpy-stl>1.0
Requires-Dist: opencv-contrib-python>=4.7.0
Requires-Dist: pandas>=0.25
Requires-Dist: pyevtk>=1.0
Requires-Dist: scipy>=1.3.1
Dynamic: author
Dynamic: author-email
Dynamic: classifier
Dynamic: home-page
Dynamic: license
Dynamic: license-file
Dynamic: requires-dist
Dynamic: summary
